pluxtools/__init__.py
pluxtools/converter.py
pluxtools/metrics.py
pluxtools-0.1.0.dist-info/METADATA
pluxtools-0.1.0.dist-info/WHEEL
pluxtools-0.1.0.dist-info/top_level.txt
pluxtools-0.1.0.dist-info/RECORD
