Metadata-Version: 2.4
Name: pluxtools
Version: 0.1.0
Summary: Convert .plux files to image formats and compute surface heterogeneity metrics.
Author-email: DrATedder <a.tedder@bradford.ac.uk>
Project-URL: Homepage, https://github.com/DrATedder/pluxtools
Project-URL: Repository, https://github.com/DrATedder/pluxtools
Keywords: plux,image,surface,metrics,heterogeneity
Classifier: Programming Language :: Python :: 3
Classifier: Operating System :: OS Independent
Requires-Python: >=3.7
Requires-Dist: numpy
Requires-Dist: pandas
Requires-Dist: scikit-image
Requires-Dist: opencv-python
Requires-Dist: tqdm
Requires-Dist: Pillow
